<?xml version="1.0" encoding="utf-8" ?>
<dwsync>
<file name="image.png" server="C:/AppServ/www/regional/" local="127440583820000000" remote="127440583820000000" />
<file name="NetByte Design Studio - 0926.png" server="C:/AppServ/www/regional/" local="129788363702179824" remote="129788363700000000" />
<file name="NetByte Design Studio - 1349.png" server="C:/AppServ/www/regional/" local="127318213260000000" remote="127318213260000000" />
<file name="NetByte Design Studio - 1344.png" server="C:/AppServ/www/regional/" local="127318215720000000" remote="127318215720000000" />
<file name="NetByte Design Studio - 1351.png" server="C:/AppServ/www/regional/" local="127318212500000000" remote="127318212500000000" />
<file name="NetByte Design Studio - 1552.png" server="C:/AppServ/www/regional/" local="127318219800000000" remote="127318219800000000" />
<file name="NetByte Design Studio - 0925.png" server="C:/AppServ/www/regional/" local="129788363699879821" remote="129788363690000000" />
<file name="header background.jpg" server="C:/AppServ/www/regional/" local="129856304709281518" remote="129856304700000000" />
<file name="banner_green.jpg" server="C:/AppServ/www/regional/" local="129856304057034211" remote="129856304050000000" />
<file name="reporte.png" server="C:/AppServ/www/regional/" local="127423066580000000" remote="127423066580000000" />
<file name="logout1.png" server="C:/AppServ/www/regional/" local="127309407680000000" remote="127309407680000000" />
<file name="editar.png" server="C:/AppServ/www/regional/" local="127309404900000000" remote="127309404900000000" />
<file name="NetByte Design Studio - 0555.png" server="C:/AppServ/www/regional/" local="129788362940078757" remote="129788362940000000" />
</dwsync>